pms_trt/__init__.py
pms_trt/_common.py
pms_trt/_io_binding.py
pms_trt/_logger.py
pms_trt/_patcher.py
pms_trt/_session.py
pms_trt/_utils.py
pms_trt-0.1.3.dist-info/METADATA
pms_trt-0.1.3.dist-info/WHEEL
pms_trt-0.1.3.dist-info/RECORD
