Metadata-Version: 2.1
Name: pms-trt
Version: 0.1.3
Summary: Package for TensorRT
Author: HyeongSeok Kim
Author-email: tiryul@gmail.com
Requires-Python: >=3.10,<4.0
Classifier: Programming Language :: Python :: 3
Classifier: Programming Language :: Python :: 3.10
Classifier: Programming Language :: Python :: 3.11
Classifier: Programming Language :: Python :: 3.12
Requires-Dist: albumentations (>=1.4.1,<2.0.0)
Requires-Dist: cuda-python (>=12.4.0,<13.0.0)
Requires-Dist: loguru (>=0.7.2,<0.8.0)
Requires-Dist: numpy (>=1.26.4,<2.0.0)
Requires-Dist: tensorrt (==8.6.1.post1)
Requires-Dist: tensorrt-bindings (==8.6.1)
Requires-Dist: tensorrt-libs (==8.6.1)
